README.md
setup.py
decotimer/__init__.py
decotimer/constants.py
decotimer/keys.py
decotimer/repeat.py
decotimer/timer.py
decotimer/wait.py
decotimer.egg-info/PKG-INFO
decotimer.egg-info/SOURCES.txt
decotimer.egg-info/dependency_links.txt
decotimer.egg-info/top_level.txt