Metadata-Version: 2.1
Name: decotimer
Version: 1.0.1
Summary: decotimer
Home-page: https://github.com/excp281/decotimer
Author: excp281
Author-email: excp281@gmail.com
License: UNKNOWN
Platform: UNKNOWN
Classifier: Programming Language :: Python :: 3
Classifier: License :: OSI Approved :: MIT License
Classifier: Operating System :: OS Independent
Requires-Python: >=3.6
